datopsy/__init__.py
datopsy_ai-1.0.dist-info/METADATA
datopsy_ai-1.0.dist-info/WHEEL
datopsy_ai-1.0.dist-info/top_level.txt
datopsy_ai-1.0.dist-info/RECORD
