Metadata-Version: 2.1
Name: datopsy-ai
Version: 1.0
Summary: A scalable and configurable DataOps framework.
Home-page: https://github.com/udyam-ai/datopsy-ai
Author: Udyam AI
Author-email: 
License: Apache-2.0
Classifier: Intended Audience :: Developers
Classifier: Intended Audience :: Education
Classifier: Intended Audience :: Science/Research
Classifier: Programming Language :: Python :: 3.5
Classifier: Programming Language :: Python :: 3.6
Classifier: Programming Language :: Python :: 3.7
Classifier: Programming Language :: Python :: 3.8
Classifier: Programming Language :: Python :: 3.9
Classifier: Programming Language :: Python :: 3.10
Classifier: Programming Language :: Python :: 3.11
Classifier: License :: OSI Approved :: MIT License
Classifier: Operating System :: OS Independent
Classifier: Topic :: Software Development :: Libraries
Classifier: Topic :: Software Development :: Libraries :: Python Modules
Requires-Dist: pandas
Requires-Dist: scikit-learn
Requires-Dist: numpy
